BDQuaternions-0.2.16.dist-info/NOTICE.txt
BDQuaternions-0.2.16.dist-info/RECORD
BDQuaternions-0.2.16.dist-info/WHEEL
BDQuaternions-0.2.16.dist-info/METADATA
BDQuaternions-0.2.16.dist-info/LICENSE.txt
BDQuaternions-0.2.16.dist-info/top_level.txt
BDQuaternions/_quaternion_operations.cpython-38-x86_64-linux-gnu.so
BDQuaternions/Rotation.pxd
BDQuaternions/EulerAngles.cpython-38-x86_64-linux-gnu.so
BDQuaternions/EulerAnglesConventions.pxd
BDQuaternions/EulerAngles.pxd
BDQuaternions/Rotation.cpython-38-x86_64-linux-gnu.so
BDQuaternions/_quaternion_operations.pxd
BDQuaternions/functions.pxd
BDQuaternions/Quaternion.cpython-38-x86_64-linux-gnu.so
BDQuaternions/UnitQuaternion.cpython-38-x86_64-linux-gnu.so
BDQuaternions/_helpers.pxd
BDQuaternions/_helpers.cpython-38-x86_64-linux-gnu.so
BDQuaternions/Quaternion.pxd
BDQuaternions/utils.pxd
BDQuaternions/functions.cpython-38-x86_64-linux-gnu.so
BDQuaternions/__init__.py
BDQuaternions/utils.cpython-38-x86_64-linux-gnu.so
BDQuaternions/EulerAnglesConventions.cpython-38-x86_64-linux-gnu.so
BDQuaternions/UnitQuaternion.pxd
BDQuaternions/_version.py
BDQuaternions/__init__.pxd
